value_predictor/__init__.py
value_predictor/value_predictor.py
value_predictor-0.0.1.dist-info/licenses/LICENSE
value_predictor-0.0.1.dist-info/METADATA
value_predictor-0.0.1.dist-info/WHEEL
value_predictor-0.0.1.dist-info/top_level.txt
value_predictor-0.0.1.dist-info/RECORD
